{
  "project_info": {
    "project_number": "692021231109",
    "project_id": "shopping-list-cff18",
    "storage_bucket": "shopping-list-cff18.firebasestorage.app"
  },
  "client": [
    {
      "client_info": {
        "mobilesdk_app_id": "1:692021231109:android:e7c792f19c9131befe666c",
        "android_client_info": {
          "package_name": "ipca.example.shoppinglist"
        }
      },
      "oauth_client": [],
      "api_key": [
        {
          "current_key": "AIzaSyDIEZpVqzyCFxYRoaO-uFml66P-J3zccb4"
        }
      ],
      "services": {
        "appinvite_service": {
          "other_platform_oauth_client": []
        }
      }
    }
  ],
  "configuration_version": "1"
}